<?xml version="1.0" encoding="utf-8"?>
<Defs>
  <StorytellerDef ParentName="BaseStoryteller" Name="LovecraftStoryteller">
    <defName>Lovecraft</defName>
    <label>H.P. Lovecraft</label>
    <description>In Lovecraft's tales, protagonists often face their own mortality and insignificance in the universe. Threats to your colony and its sanity will be constant. Can your colony survive a cosmic horror tale?</description>
    <portraitLarge>Lovecraft1.1</portraitLarge>
    <portraitTiny>Lovecraft1.2</portraitTiny>
    <listOrder>50</listOrder>
    <comps>
      <!-- Intro -->
      <li Class="StorytellerCompProperties_ClassicIntro" />
      <!-- Home threats -->
      <li Class="HPLovecraft.StorytellerCompProperties_OmenThreatCycle">
        <category>ThreatBig</category>
        <minDaysPassed>11.0</minDaysPassed>
        <onDays>4.6</onDays>
        <offDays>6.0</offDays>
        <minSpacingDays>1.9</minSpacingDays>
        <numIncidentsRange>1~2</numIncidentsRange>
        <forceRaidEnemyBeforeDaysPassed>20</forceRaidEnemyBeforeDaysPassed>
        <disallowedTargetTags>
          <li>Map_RaidBeacon</li>
        </disallowedTargetTags>
      </li>
      <li Class="StorytellerCompProperties_OnOffCycle">
        <allowedTargetTags>
          <li>Map_RaidBeacon</li>
        </allowedTargetTags>
        <onDays>1.0</onDays>
        <offDays>0.5</offDays>
        <minSpacingDays>0.04</minSpacingDays>
        <applyRaidBeaconThreatMtbFactor>true</applyRaidBeaconThreatMtbFactor>
        <numIncidentsRange>1~2</numIncidentsRange>
        <category>RaidBeacon</category>
      </li>
      <li Class="StorytellerCompProperties_OnOffCycle">
        <category>ThreatSmall</category>
        <minDaysPassed>11.0</minDaysPassed>
        <onDays>4.6</onDays>
        <offDays>6.0</offDays>
        <numIncidentsRange>0.2~1</numIncidentsRange>
      </li>
      <!-- Home misc -->
      <li Class="StorytellerCompProperties_CategoryMTB">
        <category>Misc</category>
        <allowedTargetTags>
          <li>Map_PlayerHome</li>
        </allowedTargetTags>
        <minDaysPassed>5</minDaysPassed>
        <mtbDays>3</mtbDays>
      </li>
      <li Class="StorytellerCompProperties_ShipChunkDrop" />
      <li Class="StorytellerCompProperties_Disease">
        <minDaysPassed>9</minDaysPassed>
        <category>DiseaseHuman</category>
      </li>
      <li Class="StorytellerCompProperties_Disease">
        <minDaysPassed>9</minDaysPassed>
        <category>DiseaseAnimal</category>
      </li>
      <!-- Ally/neutral interaction -->
      <li Class="StorytellerCompProperties_FactionInteraction">
        <incident>RaidFriendly</incident>
        <baseIncidentsPerYear>15</baseIncidentsPerYear>
        <minSpacingDays>0.4</minSpacingDays>
        <fullAlliesOnly>true</fullAlliesOnly>
        <minDanger>High</minDanger>
      </li>
      <li Class="StorytellerCompProperties_FactionInteraction">
        <incident>TraderCaravanArrival</incident>
        <minDaysPassed>5</minDaysPassed>
        <baseIncidentsPerYear>5</baseIncidentsPerYear>
        <minSpacingDays>6</minSpacingDays>
        <allowedTargetTags>
          <li>Map_PlayerHome</li>
        </allowedTargetTags>
      </li>
      <li Class="StorytellerCompProperties_FactionInteraction">
        <incident>VisitorGroup</incident>
        <minDaysPassed>3</minDaysPassed>
        <baseIncidentsPerYear>4</baseIncidentsPerYear>
        <minSpacingDays>5</minSpacingDays>
        <allowedTargetTags>
          <li>Map_PlayerHome</li>
        </allowedTargetTags>
      </li>
      <li Class="StorytellerCompProperties_FactionInteraction">
        <incident>TravelerGroup</incident>
        <minDaysPassed>1</minDaysPassed>
        <baseIncidentsPerYear>6</baseIncidentsPerYear>
        <minSpacingDays>1</minSpacingDays>
        <allowedTargetTags>
          <li>Map_PlayerHome</li>
        </allowedTargetTags>
      </li>
      <!-- Caravan / temp map -->
      <li Class="StorytellerCompProperties_CategoryIndividualMTBByBiome">
        <category>Misc</category>
        <allowedTargetTags>
          <li>Caravan</li>
          <li>Map_TempIncident</li>
        </allowedTargetTags>
      </li>
      <li Class="StorytellerCompProperties_CategoryIndividualMTBByBiome">
        <category>ThreatSmall</category>
        <applyCaravanVisibility>true</applyCaravanVisibility>
        <allowedTargetTags>
          <li>Caravan</li>
          <li>Map_TempIncident</li>
        </allowedTargetTags>
      </li>
      <li Class="StorytellerCompProperties_CategoryIndividualMTBByBiome">
        <category>ThreatBig</category>
        <applyCaravanVisibility>true</applyCaravanVisibility>
        <allowedTargetTags>
          <li>Caravan</li>
          <li>Map_TempIncident</li>
        </allowedTargetTags>
      </li>
      <!-- World -->
      <li Class="StorytellerCompProperties_JourneyOffer" />
      <li Class="StorytellerCompProperties_CategoryMTB">
        <category>WorldQuest</category>
        <allowedTargetTags>
          <li>World</li>
        </allowedTargetTags>
        <minDaysPassed>6</minDaysPassed>
        <mtbDays>7.5</mtbDays>
        <mtbDaysFactorByDaysPassedCurve>
          <points>
            <li>(6, 5)</li>
            <li>(40, 1)</li>
          </points>
        </mtbDaysFactorByDaysPassedCurve>
      </li>
      <li Class="StorytellerCompProperties_CategoryMTB">
        <category>Misc</category>
        <allowedTargetTags>
          <li>World</li>
        </allowedTargetTags>
        <minDaysPassed>15</minDaysPassed>
        <mtbDays>15</mtbDays>
      </li>
      <!-- Orbital -->
      <li Class="StorytellerCompProperties_OnOffCycle">
        <incident>OrbitalTraderArrival</incident>
        <onDays>7</onDays>
        <offDays>8</offDays>
        <numIncidentsRange>1</numIncidentsRange>
      </li>
    </comps>
  </StorytellerDef>
  <StorytellerDef ParentName="LovecraftStoryteller">
    <defName>Lovecraft_DoublePop</defName>
    <label>H.P. Lovecraft (Population x2)</label>
    <description>In Lovecraft's tales, protagonists often face their own mortality and insignificance in the universe. Threats to your colony and its sanity will be constant. Can your colony survive a cosmic horror tale?\n\nDoubles normal population caps during gameplay.</description>
    <portraitLarge>LovecraftX21.1</portraitLarge>
    <portraitTiny>LovecraftX21.2</portraitTiny>
    <listOrder>51</listOrder>
    <populationIntentFactorFromPopCurve>
      <points>
        <li>0,  8.0</li>
        <li>2,  2.0</li>
        <li>10,  1.0</li>
        <li>18,  0.4</li>
        <li>24, 0.0</li>
        <li>40,-1.0</li>
      </points>
    </populationIntentFactorFromPopCurve>
  </StorytellerDef>
</Defs>